{"arch_packages": "mips64_octeonplus", "build_at": "2023-04-30 05:12:42", "default_packages": ["base-files", "busybox", "ca-bundle", "dnsmasq", "dropbear", "e2fsprogs", "firewall", "fstools", "ip6tables", "iptables", "kmod-ipt-offload", "libc", "libgcc", "libustream-wolfssl", "logd", "mkf2fs", "mtd", "netifd", "odhcp6c", "odhcpd-ipv6only", "opkg", "ppp", "ppp-mod-pppoe", "procd", "uci", "uclient-fetch", "urandom-seed", "urngd"], "device_packages": [], "id": "itus_shield-router", "image_path": "releases/21.02.7/targets/octeon/generic", "image_prefix": "openwrt-21.02.7-octeon-itus_shield-router", "images": [{"filesystem": "squashfs", "name": "openwrt-21.02.7-octeon-itus_shield-router-squashfs-sysupgrade.tar", "sha256": "a3d2c74c579b0e9676047c15dca49621403aeca17e03717c69e1903bd64b7704", "type": "sysupgrade"}, {"filesystem": "initramfs", "name": "openwrt-21.02.7-octeon-itus_shield-router-initramfs-kernel.bin", "sha256": "e6fd7f96b2c65c1ac82ded21d58c3bd5becf5e70f809a7f83847bff4a6170b02", "type": "kernel"}], "metadata_version": 1, "source_date_epoch": "1681737336", "supported_devices": ["itus,shield-router"], "target": "octeon/generic", "titles": [{"model": "Shield Router", "vendor": "Itus Networks"}], "version_code": "r16847-f8282da11e", "version_number": "21.02.7"}