{"arch_packages": "mipsel_24kc", "build_at": "2021-09-02 01:03:19", "default_packages": ["base-files", "busybox", "ca-bundle", "dnsmasq", "dropbear", "firewall", "fstools", "ip6tables", "iptables", "kmod-gpio-button-hotplug", "kmod-ipt-offload", "kmod-leds-gpio", "libc", "libgcc", "libustream-wolfssl", "logd", "mtd", "netifd", "odhcp6c", "odhcpd-ipv6only", "opkg", "ppp", "ppp-mod-pppoe", "procd", "uci", "uclient-fetch", "urandom-seed", "urngd", "wpad-basic-wolfssl"], "device_packages": ["kmod-mt7603", "kmod-mt76x2", "kmod-usb3", "kmod-usb-ledtrig-usbport"], "id": "asus_rt-ac57u", "image_path": "releases/21.02.0/targets/ramips/mt7621", "image_prefix": "openwrt-21.02.0-ramips-mt7621-asus_rt-ac57u", "images": [{"filesystem": "initramfs", "name": "openwrt-21.02.0-ramips-mt7621-asus_rt-ac57u-initramfs-kernel.bin", "sha256": "2641e799ac277522dd69a93341c9e5a018d8d28eeb1591326a7b9b4f85620789", "type": "kernel"}, {"filesystem": "squashfs", "name": "openwrt-21.02.0-ramips-mt7621-asus_rt-ac57u-squashfs-sysupgrade.bin", "sha256": "9b6e869619d627e4ff3890841a07183e298c8c5a32675036952b42055b036a79", "type": "sysupgrade"}], "metadata_version": 1, "source_date_epoch": "1630448408", "supported_devices": ["asus,rt-ac57u"], "target": "ramips/mt7621", "titles": [{"model": "RT-AC57U", "vendor": "ASUS"}], "version_code": "r16279-5cc0535800", "version_number": "21.02.0"}