{"arch_packages": "arm_xscale", "build_at": "2023-12-03 22:10:35", "default_packages": ["base-files", "busybox", "ca-bundle", "dnsmasq", "dropbear", "firewall4", "fstools", "kmod-nft-offload", "kmod-usb2", "libc", "libgcc", "libustream-wolfssl", "logd", "mtd", "netifd", "nftables", "odhcp6c", "odhcpd-ipv6only", "opkg", "ppp", "ppp-mod-pppoe", "procd", "procd-seccomp", "procd-ujail", "uboot-envtools", "uci", "uclient-fetch", "urandom-seed", "urngd"], "device_packages": ["kmod-mvsdio"], "id": "cisco_on100", "image_path": "releases/22.03.6/targets/kirkwood/generic", "image_prefix": "openwrt-22.03.6-kirkwood-cisco_on100", "images": [{"filesystem": "squashfs", "name": "openwrt-22.03.6-kirkwood-cisco_on100-squashfs-factory.bin", "sha256": "75826de3b8ae73a741bc58d3c39891df13e198769cb5df74024f61311634d7ea", "sha256_unsigned": "75826de3b8ae73a741bc58d3c39891df13e198769cb5df74024f61311634d7ea", "type": "factory"}, {"filesystem": "initramfs", "name": "openwrt-22.03.6-kirkwood-cisco_on100-initramfs-uImage", "sha256": "c1f9c33c80e0afcdd6d091ba394ca4db35c7b2f53b818a283b78f45d3e262e58", "sha256_unsigned": "c1f9c33c80e0afcdd6d091ba394ca4db35c7b2f53b818a283b78f45d3e262e58", "type": "kernel"}, {"filesystem": "squashfs", "name": "openwrt-22.03.6-kirkwood-cisco_on100-squashfs-sysupgrade.bin", "sha256": "bab0a9bf35551a459c76b3a94684ca89b9466175446e76a8b573b5ce55e5432b", "sha256_unsigned": "7be74982d19ff9e3815d97174054d5ec4916dc35cc35db6a72a112f1fb3a639c", "type": "sysupgrade"}], "metadata_version": 1, "source_date_epoch": 1700936337, "supported_devices": ["cisco,on100", "on100"], "target": "kirkwood/generic", "titles": [{"model": "ON100", "vendor": "Cisco Systems"}], "version_code": "r20265-f85a79bcb4", "version_number": "22.03.6"}