{"arch_packages": "mips_24kc", "build_at": "2022-10-17 19:55:47", "default_packages": ["base-files", "busybox", "ca-bundle", "dnsmasq", "dropbear", "firewall", "fstools", "ip6tables", "iptables", "kmod-ath9k", "kmod-gpio-button-hotplug", "kmod-ipt-offload", "libc", "libgcc", "libustream-wolfssl", "logd", "mtd", "netifd", "odhcp6c", "odhcpd-ipv6only", "opkg", "ppp", "ppp-mod-pppoe", "procd", "swconfig", "uboot-envtools", "uci", "uclient-fetch", "urandom-seed", "urngd", "wpad-basic-wolfssl"], "device_packages": ["kmod-usb-ohci", "kmod-usb2", "kmod-usb-ledtrig-usbport", "kmod-leds-reset", "kmod-owl-loader"], "id": "netgear_wndr3800ch", "image_path": "releases/21.02.5/targets/ath79/generic", "image_prefix": "openwrt-21.02.5-ath79-generic-netgear_wndr3800ch", "images": [{"filesystem": "squashfs", "name": "openwrt-21.02.5-ath79-generic-netgear_wndr3800ch-squashfs-sysupgrade.bin", "sha256": "8de911b2e814676772155fd43cf77ad493b19737f7681a18bbc91b1ea578c5a2", "type": "sysupgrade"}, {"filesystem": "initramfs", "name": "openwrt-21.02.5-ath79-generic-netgear_wndr3800ch-initramfs-kernel.bin", "sha256": "baceee1d4d17a9cf5149cec10bbe36edc0dcf26bef1c859dfccf6155b7cc2790", "type": "kernel"}, {"filesystem": "squashfs", "name": "openwrt-21.02.5-ath79-generic-netgear_wndr3800ch-squashfs-factory.img", "sha256": "df1b706cd420986caa4942a010c8d23ec58e80f4bb0ae759b620bdbb1f04b03e", "type": "factory"}], "metadata_version": 1, "source_date_epoch": "1665688598", "supported_devices": ["netgear,wndr3800ch", "wndr3700"], "target": "ath79/generic", "titles": [{"model": "WNDR3800CH", "vendor": "NETGEAR"}], "version_code": "r16688-fa9a932fdb", "version_number": "21.02.5"}