{"arch_packages": "mipsel_24kc", "build_at": "2023-10-12 01:56:24", "default_packages": ["base-files", "busybox", "ca-bundle", "dnsmasq", "dropbear", "firewall4", "fstools", "kmod-gpio-button-hotplug", "kmod-leds-gpio", "kmod-nft-offload", "kmod-rt2800-soc", "libc", "libgcc", "libustream-mbedtls", "logd", "mtd", "netifd", "nftables", "odhcp6c", "odhcpd-ipv6only", "opkg", "ppp", "ppp-mod-pppoe", "procd", "procd-seccomp", "swconfig", "uci", "uclient-fetch", "urandom-seed", "urngd", "wpad-basic-mbedtls"], "device_packages": [], "id": "omnima_miniembplug", "image_path": "releases/23.05.0/targets/ramips/rt305x", "image_prefix": "openwrt-23.05.0-ramips-rt305x-omnima_miniembplug", "images": [{"filesystem": "squashfs", "name": "openwrt-23.05.0-ramips-rt305x-omnima_miniembplug-squashfs-sysupgrade.bin", "sha256": "75f94b75554419ea00ea84a2e2b9b1edded73e1fdfb0135b062a1ed2c7ba081c", "sha256_unsigned": "4aec477d884c41cb58a3e3aef8c10cec2753fa2efe7674d96ff737a5ea5977aa", "type": "sysupgrade"}, {"filesystem": "initramfs", "name": "openwrt-23.05.0-ramips-rt305x-omnima_miniembplug-initramfs-kernel.bin", "sha256": "bd892594725c62ffdc2ff46390a26154776f60ef8d9e5ac29f1c353659ba2828", "sha256_unsigned": "bd892594725c62ffdc2ff46390a26154776f60ef8d9e5ac29f1c353659ba2828", "type": "kernel"}], "metadata_version": 1, "source_date_epoch": 1696887935, "supported_devices": ["omnima,miniembplug", "miniembplug"], "target": "ramips/rt305x", "titles": [{"model": "MiniEMBPlug", "vendor": "Omnima"}], "version_code": "r23497-6637af95aa", "version_number": "23.05.0"}