{"arch_packages": "mips_4kec", "build_at": "2023-01-04 17:56:28", "default_packages": ["base-files", "busybox", "ca-bundle", "dropbear", "ethtool", "firewall4", "fstools", "ip-bridge", "ip-full", "kmod-gpio-button-hotplug", "kmod-nft-offload", "libc", "libgcc", "libustream-wolfssl", "logd", "mtd", "netifd", "nftables", "odhcp6c", "opkg", "procd", "procd-seccomp", "procd-ujail", "tc-bpf", "uboot-envtools", "uci", "uclient-fetch", "urandom-seed", "urngd"], "device_packages": [], "id": "zyxel_gs1900-24-v1", "image_path": "releases/22.03.3/targets/realtek/rtl838x", "image_prefix": "openwrt-22.03.3-realtek-rtl838x-zyxel_gs1900-24-v1", "images": [{"filesystem": "initramfs", "name": "openwrt-22.03.3-realtek-rtl838x-zyxel_gs1900-24-v1-initramfs-kernel.bin", "sha256": "402298c7a4ec31aae2acc8860984aa65d2e6173040ce96f45a7642d681104fac", "sha256_unsigned": "402298c7a4ec31aae2acc8860984aa65d2e6173040ce96f45a7642d681104fac", "type": "kernel"}, {"filesystem": "squashfs", "name": "openwrt-22.03.3-realtek-rtl838x-zyxel_gs1900-24-v1-squashfs-sysupgrade.bin", "sha256": "9982750b960e680191a827e45a416ced87944901063b6c07618d47c1962b9eba", "sha256_unsigned": "f8b6f90ca7ef6364b4d7121c25ce33b8425e7aea0eafd4ec8f7845d78e78715c", "type": "sysupgrade"}], "metadata_version": 1, "source_date_epoch": 1672705461, "supported_devices": ["zyxel,gs1900-24-v1"], "target": "realtek/rtl838x", "titles": [{"model": "GS1900-24", "variant": "v1", "vendor": "ZyXEL"}], "version_code": "r20028-43d71ad93e", "version_number": "22.03.3"}