{"arch_packages": "arm_cortex-a7_neon-vfpv4", "build_at": "2022-09-03 23:45:32", "default_packages": ["ath10k-board-qca4019", "ath10k-firmware-qca4019-ct", "base-files", "busybox", "ca-bundle", "dnsmasq", "dropbear", "firewall4", "fstools", "kmod-ath10k-ct", "kmod-gpio-button-hotplug", "kmod-leds-gpio", "kmod-nft-offload", "kmod-usb-dwc3", "kmod-usb-dwc3-qcom", "kmod-usb3", "libc", "libgcc", "libustream-wolfssl", "logd", "mtd", "netifd", "nftables", "odhcp6c", "odhcpd-ipv6only", "opkg", "ppp", "ppp-mod-pppoe", "procd", "procd-seccomp", "procd-ujail", "swconfig", "uboot-envtools", "uci", "uclient-fetch", "urandom-seed", "urngd", "wpad-basic-wolfssl"], "device_packages": [], "id": "compex_wpj419", "image_path": "releases/22.03.0/targets/ipq40xx/generic", "image_prefix": "openwrt-22.03.0-ipq40xx-generic-compex_wpj419", "images": [{"filesystem": "squashfs", "name": "openwrt-22.03.0-ipq40xx-generic-compex_wpj419-squashfs-nand-sysupgrade.bin", "sha256": "0c4dd07d861d0164f00f21228d91fae7ccfaf5bcd3614f9df50bfe7ff2fefa81", "sha256_unsigned": "466f0dc143ccd723f6ad92431692e84fdf65cc69fabe4a5f902ab015423e0b5f", "type": "nand-sysupgrade"}, {"filesystem": "squashfs", "name": "openwrt-22.03.0-ipq40xx-generic-compex_wpj419-squashfs-nand-factory.ubi", "sha256": "670dae2fdbae175ba1749fa535309996706dd26fb65ac8ecce5b7f1944a92617", "sha256_unsigned": "670dae2fdbae175ba1749fa535309996706dd26fb65ac8ecce5b7f1944a92617", "type": "nand-factory"}, {"filesystem": "initramfs", "name": "openwrt-22.03.0-ipq40xx-generic-compex_wpj419-initramfs-fit-uImage.itb", "sha256": "c3a4603578e5b682aa06b784ebb03cd32c1b5e489f465c22183b63610a4b12e8", "sha256_unsigned": "c3a4603578e5b682aa06b784ebb03cd32c1b5e489f465c22183b63610a4b12e8", "type": "kernel"}], "metadata_version": 1, "source_date_epoch": 1662173734, "supported_devices": ["compex,wpj419"], "target": "ipq40xx/generic", "titles": [{"model": "WPJ419", "vendor": "Compex"}], "version_code": "r19685-512e76967f", "version_number": "22.03.0"}