{"arch_packages": "mips_24kc", "build_at": "2022-10-10 17:10:15", "default_packages": ["base-files", "busybox", "ca-bundle", "dnsmasq", "dropbear", "firewall", "fstools", "ip6tables", "iptables", "kmod-ath9k", "kmod-gpio-button-hotplug", "kmod-ipt-offload", "libc", "libgcc", "libustream-wolfssl", "logd", "mtd", "netifd", "odhcp6c", "odhcpd-ipv6only", "opkg", "ppp", "ppp-mod-pppoe", "procd", "swconfig", "uboot-envtools", "uci", "uclient-fetch", "urandom-seed", "urngd", "wpad-basic-wolfssl"], "device_packages": ["kmod-ath10k-ct", "ath10k-firmware-qca9888-ct"], "id": "dlink_dir-842-c3", "image_path": "releases/21.02.4/targets/ath79/generic", "image_prefix": "openwrt-21.02.4-ath79-generic-dlink_dir-842-c3", "images": [{"filesystem": "squashfs", "name": "openwrt-21.02.4-ath79-generic-dlink_dir-842-c3-squashfs-sysupgrade.bin", "sha256": "22634533cca40ba9a2aa4bc8f459df1c31a5bc770ac109bcf2aa4acbd754a85b", "type": "sysupgrade"}, {"filesystem": "squashfs", "name": "openwrt-21.02.4-ath79-generic-dlink_dir-842-c3-squashfs-factory.bin", "sha256": "057730c2170e0297df57addbe6cb721a4e75e429b50aca53fb027faa4caf7de2", "type": "factory"}, {"filesystem": "initramfs", "name": "openwrt-21.02.4-ath79-generic-dlink_dir-842-c3-initramfs-kernel.bin", "sha256": "817c5de5b4d27f9ba52a7ba8a2d64913254a206de76522825893a42c916e9ccd", "type": "kernel"}], "metadata_version": 1, "source_date_epoch": "1665330221", "supported_devices": ["dlink,dir-842-c3"], "target": "ath79/generic", "titles": [{"model": "DIR-842", "variant": "C3", "vendor": "D-Link"}], "version_code": "r16685-82ebc173b3", "version_number": "21.02.4"}