{"arch_packages": "mips_4kec", "build_at": "2023-04-10 05:17:12", "default_packages": ["base-files", "busybox", "ca-bundle", "dropbear", "ethtool", "firewall4", "fstools", "ip-bridge", "ip-full", "kmod-gpio-button-hotplug", "kmod-nft-offload", "libc", "libgcc", "libustream-wolfssl", "logd", "mtd", "netifd", "nftables", "odhcp6c", "opkg", "procd", "procd-seccomp", "procd-ujail", "tc-bpf", "uboot-envtools", "uci", "uclient-fetch", "urandom-seed", "urngd"], "device_packages": [], "id": "zyxel_gs1900-24e", "image_path": "releases/22.03.4/targets/realtek/rtl838x", "image_prefix": "openwrt-22.03.4-realtek-rtl838x-zyxel_gs1900-24e", "images": [{"filesystem": "initramfs", "name": "openwrt-22.03.4-realtek-rtl838x-zyxel_gs1900-24e-initramfs-kernel.bin", "sha256": "dc6ae9d74782ea6a7764c7de29766642b5ab1979ee6de669f86f5eecb94319b1", "sha256_unsigned": "dc6ae9d74782ea6a7764c7de29766642b5ab1979ee6de669f86f5eecb94319b1", "type": "kernel"}, {"filesystem": "squashfs", "name": "openwrt-22.03.4-realtek-rtl838x-zyxel_gs1900-24e-squashfs-sysupgrade.bin", "sha256": "6ba9458973c03b69ed320b7f1a2163dbe0f9d1a03306b169aa442255ced56d68", "sha256_unsigned": "9404c15eec8d05113806fcd55b982353f82f61cb8a7524ef6d9535efcd0efcc1", "type": "sysupgrade"}], "metadata_version": 1, "source_date_epoch": 1681043266, "supported_devices": ["zyxel,gs1900-24e"], "target": "realtek/rtl838x", "titles": [{"model": "GS1900-24E", "vendor": "ZyXEL"}], "version_code": "r20123-38ccc47687", "version_number": "22.03.4"}