{"arch_packages": "mipsel_24kc", "build_at": "2023-01-04 14:57:36", "default_packages": ["base-files", "busybox", "ca-bundle", "dnsmasq", "dropbear", "firewall4", "fstools", "kmod-gpio-button-hotplug", "kmod-leds-gpio", "kmod-nft-offload", "kmod-rt2800-soc", "libc", "libgcc", "libustream-wolfssl", "logd", "mtd", "netifd", "nftables", "odhcp6c", "odhcpd-ipv6only", "opkg", "ppp", "ppp-mod-pppoe", "procd", "procd-seccomp", "procd-ujail", "swconfig", "uci", "uclient-fetch", "urandom-seed", "urngd", "wpad-basic-wolfssl"], "device_packages": ["kmod-mt76x2"], "id": "phicomm_psg1218b", "image_path": "releases/22.03.3/targets/ramips/mt7620", "image_prefix": "openwrt-22.03.3-ramips-mt7620-phicomm_psg1218b", "images": [{"filesystem": "initramfs", "name": "openwrt-22.03.3-ramips-mt7620-phicomm_psg1218b-initramfs-kernel.bin", "sha256": "2d7d2d22bc63c2f3aed66683a77aa9bf5fb9ac17056f1d2f800ac2bfa4be64e0", "sha256_unsigned": "2d7d2d22bc63c2f3aed66683a77aa9bf5fb9ac17056f1d2f800ac2bfa4be64e0", "type": "kernel"}, {"filesystem": "squashfs", "name": "openwrt-22.03.3-ramips-mt7620-phicomm_psg1218b-squashfs-sysupgrade.bin", "sha256": "3a82dead350766dafa95f08ffcb80b0eb4dce42592c8be9b0d4fb823bb6354ae", "sha256_unsigned": "c1a10d2123fb358050f4b8c80583eee0f51272d97097f3ba0829579ce275cea6", "type": "sysupgrade"}], "metadata_version": 1, "source_date_epoch": 1672705461, "supported_devices": ["phicomm,psg1218b", "psg1218", "psg1218b"], "target": "ramips/mt7620", "titles": [{"model": "PSG1218", "variant": "Bx", "vendor": "Phicomm"}], "version_code": "r20028-43d71ad93e", "version_number": "22.03.3"}