{"arch_packages": "mips_24kc", "build_at": "2022-10-10 02:27:30", "default_packages": ["base-files", "busybox", "ca-bundle", "dnsmasq", "dropbear", "firewall4", "fstools", "kmod-ath9k", "kmod-gpio-button-hotplug", "kmod-nft-offload", "libc", "libgcc", "libustream-wolfssl", "logd", "mtd", "netifd", "nftables", "odhcp6c", "odhcpd-ipv6only", "opkg", "ppp", "ppp-mod-pppoe", "procd", "procd-seccomp", "procd-ujail", "swconfig", "uboot-envtools", "uci", "uclient-fetch", "urandom-seed", "urngd", "wpad-basic-wolfssl"], "device_packages": ["kmod-usb2"], "id": "librerouter_librerouter-v1", "image_path": "releases/22.03.1/targets/ath79/generic", "image_prefix": "openwrt-22.03.1-ath79-generic-librerouter_librerouter-v1", "images": [{"filesystem": "squashfs", "name": "openwrt-22.03.1-ath79-generic-librerouter_librerouter-v1-squashfs-sysupgrade.bin", "sha256": "56ac74bb135167d75b78301043246fc8e8ee6bdd77fad42c630e8eabae51436a", "sha256_unsigned": "6cce7eafea4552b845636327e9b0bb5d0ed1789866ba49429ab960d64866ff1f", "type": "sysupgrade"}, {"filesystem": "initramfs", "name": "openwrt-22.03.1-ath79-generic-librerouter_librerouter-v1-initramfs-kernel.bin", "sha256": "2cea58e526ca52152e787cb4f741b0c9cf0c39123bb99ca017ca1d92e9b17b6f", "sha256_unsigned": "2cea58e526ca52152e787cb4f741b0c9cf0c39123bb99ca017ca1d92e9b17b6f", "type": "kernel"}], "metadata_version": 1, "source_date_epoch": 1665185696, "supported_devices": ["librerouter,librerouter-v1"], "target": "ath79/generic", "titles": [{"model": "LibreRouter", "variant": "v1", "vendor": "Librerouter"}], "version_code": "r19777-2853b6d652", "version_number": "22.03.1"}