{"arch_packages": "mips_mips32", "build_at": "2023-11-13 23:26:11", "default_packages": ["base-files", "busybox", "ca-bundle", "dnsmasq", "dropbear", "firewall4", "fstools", "kmod-gpio-button-hotplug", "kmod-nft-offload", "libc", "libgcc", "libustream-mbedtls", "logd", "mtd", "netifd", "nftables", "odhcp6c", "odhcpd-ipv6only", "opkg", "ppp", "ppp-mod-pppoe", "procd", "procd-seccomp", "procd-ujail", "swconfig", "uci", "uclient-fetch", "urandom-seed", "urngd"], "device_packages": [], "id": "brcm_bcm96328avng", "image_path": "releases/23.05.1/targets/bcm63xx/smp", "image_prefix": "openwrt-23.05.1-bcm63xx-smp-brcm_bcm96328avng", "images": [{"filesystem": "squashfs", "name": "openwrt-23.05.1-bcm63xx-smp-brcm_bcm96328avng-squashfs-cfe-4M.bin", "sha256": "ea031988d6a39e66ce67c2a60b4056c0406b5596683bc61514762121aae6576c", "sha256_unsigned": "ea031988d6a39e66ce67c2a60b4056c0406b5596683bc61514762121aae6576c", "type": "cfe-4M"}, {"filesystem": "squashfs", "name": "openwrt-23.05.1-bcm63xx-smp-brcm_bcm96328avng-squashfs-cfe-8M.bin", "sha256": "ea031988d6a39e66ce67c2a60b4056c0406b5596683bc61514762121aae6576c", "sha256_unsigned": "ea031988d6a39e66ce67c2a60b4056c0406b5596683bc61514762121aae6576c", "type": "cfe-8M"}, {"filesystem": "squashfs", "name": "openwrt-23.05.1-bcm63xx-smp-brcm_bcm96328avng-squashfs-cfe-16M.bin", "sha256": "15cea8b18f306b6a9d23c4f0fc3d4910c61318da7a3a7cca6fc04fc25be6ebc4", "sha256_unsigned": "15cea8b18f306b6a9d23c4f0fc3d4910c61318da7a3a7cca6fc04fc25be6ebc4", "type": "cfe-16M"}], "metadata_version": 1, "source_date_epoch": 1699802379, "supported_devices": ["brcm,bcm96328avng"], "target": "bcm63xx/smp", "titles": [{"model": "96328avng", "vendor": "Generic"}], "version_code": "r23619-101988c61a", "version_number": "23.05.1"}