{"arch_packages": "mips_24kc", "build_at": "2021-10-25 23:06:26", "default_packages": ["base-files", "busybox", "ca-bundle", "dnsmasq", "dropbear", "firewall", "fstools", "ip6tables", "iptables", "kmod-ath9k", "kmod-gpio-button-hotplug", "kmod-ipt-offload", "libc", "libgcc", "libustream-wolfssl", "logd", "mtd", "netifd", "odhcp6c", "odhcpd-ipv6only", "opkg", "ppp", "ppp-mod-pppoe", "procd", "swconfig", "uboot-envtools", "uci", "uclient-fetch", "urandom-seed", "urngd", "wpad-basic-wolfssl"], "device_packages": ["-kmod-ath9k", "-wpad-basic-wolfssl", "-uboot-envtools", "kmod-usb-ohci", "kmod-usb2", "fconfig"], "id": "ubnt_routerstation-pro", "image_path": "releases/21.02.1/targets/ath79/generic", "image_prefix": "openwrt-21.02.1-ath79-generic-ubnt_routerstation-pro", "images": [{"filesystem": "squashfs", "name": "openwrt-21.02.1-ath79-generic-ubnt_routerstation-pro-squashfs-factory.bin", "sha256": "61b09646a2e9822ce1e3f10a246905fb0465c298a7097fcf26e18461559f7062", "type": "factory"}, {"filesystem": "squashfs", "name": "openwrt-21.02.1-ath79-generic-ubnt_routerstation-pro-squashfs-sysupgrade.bin", "sha256": "9f40986352f4abffbf69ccca51196e2688bb607e003d73e5c9702cb50c3c8ddf", "type": "sysupgrade"}, {"filesystem": "initramfs", "name": "openwrt-21.02.1-ath79-generic-ubnt_routerstation-pro-initramfs-kernel.bin", "sha256": "9370ceb7558d42f43a8000e669864a096def7768731925153bf43e13329182fe", "type": "kernel"}], "metadata_version": 1, "source_date_epoch": "1635066095", "supported_devices": ["ubnt,routerstation-pro", "routerstation-pro"], "target": "ath79/generic", "titles": [{"model": "RouterStation Pro", "vendor": "Ubiquiti"}], "version_code": "r16325-88151b8303", "version_number": "21.02.1"}