{"arch_packages": "mips_24kc", "build_at": "2021-09-02 01:53:02", "default_packages": ["base-files", "busybox", "ca-bundle", "dnsmasq", "dropbear", "firewall", "fstools", "ip6tables", "iptables", "kmod-ath9k", "kmod-gpio-button-hotplug", "kmod-ipt-offload", "libc", "libgcc", "libustream-wolfssl", "logd", "mtd", "netifd", "odhcp6c", "odhcpd-ipv6only", "opkg", "ppp", "ppp-mod-pppoe", "procd", "swconfig", "uboot-envtools", "uci", "uclient-fetch", "urandom-seed", "urngd", "wpad-basic-wolfssl"], "device_packages": ["kmod-usb2", "kmod-ath10k-ct", "ath10k-firmware-qca9887-ct"], "id": "glinet_gl-ar750", "image_path": "releases/21.02.0/targets/ath79/generic", "image_prefix": "openwrt-21.02.0-ath79-generic-glinet_gl-ar750", "images": [{"filesystem": "squashfs", "name": "openwrt-21.02.0-ath79-generic-glinet_gl-ar750-squashfs-sysupgrade.bin", "sha256": "50c7877dca47eb27cc041a77301929e0732217f8a781faf5d42e58bafeb31bcc", "type": "sysupgrade"}, {"filesystem": "initramfs", "name": "openwrt-21.02.0-ath79-generic-glinet_gl-ar750-initramfs-kernel.bin", "sha256": "6af9112f6955ffdbc82de15f379988f984a1f1c527e3ca41834a668045759c9e", "type": "kernel"}], "metadata_version": 1, "source_date_epoch": "1630448408", "supported_devices": ["glinet,gl-ar750", "gl-ar750"], "target": "ath79/generic", "titles": [{"model": "GL-AR750", "vendor": "GL.iNet"}], "version_code": "r16279-5cc0535800", "version_number": "21.02.0"}