{"arch_packages": "mips_24kc", "build_at": "2022-10-15 20:14:27", "default_packages": ["base-files", "busybox", "ca-bundle", "dnsmasq", "dropbear", "firewall4", "fstools", "kmod-ath9k", "kmod-gpio-button-hotplug", "kmod-nft-offload", "libc", "libgcc", "libustream-wolfssl", "logd", "mtd", "netifd", "nftables", "odhcp6c", "odhcpd-ipv6only", "opkg", "ppp", "ppp-mod-pppoe", "procd", "procd-seccomp", "procd-ujail", "swconfig", "uboot-envtools", "uci", "uclient-fetch", "urandom-seed", "urngd", "wpad-basic-wolfssl"], "device_packages": ["kmod-ath10k-ct", "ath10k-firmware-qca9984-ct"], "id": "xiaomi_aiot-ac2350", "image_path": "releases/22.03.2/targets/ath79/generic", "image_prefix": "openwrt-22.03.2-ath79-generic-xiaomi_aiot-ac2350", "images": [{"filesystem": "initramfs", "name": "openwrt-22.03.2-ath79-generic-xiaomi_aiot-ac2350-initramfs-kernel.bin", "sha256": "98da451011d106e7b0fba58ba6ca6563bf556c6dc8cd8f957526cf56c9a78197", "sha256_unsigned": "98da451011d106e7b0fba58ba6ca6563bf556c6dc8cd8f957526cf56c9a78197", "type": "kernel"}, {"filesystem": "squashfs", "name": "openwrt-22.03.2-ath79-generic-xiaomi_aiot-ac2350-squashfs-sysupgrade.bin", "sha256": "37b8e7560269c0926151105c70ccfa3e7f97b7dce50fe9c83a4a71be18daae8c", "sha256_unsigned": "072cbf0d368b67de58c9583e19707b881c3b1ad383e03acf335d5c8db15f2e9e", "type": "sysupgrade"}], "metadata_version": 1, "source_date_epoch": 1665787481, "supported_devices": ["xiaomi,aiot-ac2350"], "target": "ath79/generic", "titles": [{"model": "AIoT AC2350", "vendor": "Xiaomi"}], "version_code": "r19803-9a599fee93", "version_number": "22.03.2"}