{"arch_packages": "aarch64_generic", "build_at": "2023-01-05 01:46:08", "default_packages": ["base-files", "busybox", "ca-bundle", "dnsmasq", "dropbear", "e2fsprogs", "firewall4", "fstools", "kmod-nft-offload", "kmod-usb-dwc3", "kmod-usb-storage", "kmod-usb3", "libc", "libgcc", "libustream-wolfssl", "logd", "mkf2fs", "mtd", "netifd", "nftables", "odhcp6c", "odhcpd-ipv6only", "opkg", "partx-utils", "ppp", "ppp-mod-pppoe", "procd", "procd-seccomp", "procd-ujail", "uci", "uclient-fetch", "urandom-seed", "urngd"], "device_packages": ["layerscape-mc", "layerscape-dpl", "tfa-ls1088a-rdb-sdboot", "restool", "kmod-ahci-qoriq", "kmod-hwmon-ina2xx", "kmod-hwmon-lm90"], "id": "fsl_ls1088a-rdb-sdboot", "image_path": "releases/22.03.3/targets/layerscape/armv8_64b", "image_prefix": "openwrt-22.03.3-layerscape-armv8_64b-fsl_ls1088a-rdb-sdboot", "images": [{"filesystem": "squashfs", "name": "openwrt-22.03.3-layerscape-armv8_64b-fsl_ls1088a-rdb-sdboot-squashfs-sysupgrade.bin", "sha256": "026e0f77cf7b817dd3cb91e3eeb4af48e0c36cc73ca5aa2bf5f74faaf3212c22", "sha256_unsigned": "6a24c48e5806ffb4ea9f7fe64d1e7e6f72337c231a90b6df985ae132529604a1", "type": "sysupgrade"}, {"filesystem": "squashfs", "name": "openwrt-22.03.3-layerscape-armv8_64b-fsl_ls1088a-rdb-sdboot-squashfs-sdcard.img.gz", "sha256": "d9e3805d0090ba92e90321e9ec530390093cc5467b4ad77f953f0f2968b747fe", "sha256_unsigned": "d9e3805d0090ba92e90321e9ec530390093cc5467b4ad77f953f0f2968b747fe", "type": "sdcard"}], "metadata_version": 1, "source_date_epoch": 1672705461, "supported_devices": ["fsl,ls1088a-rdb-sdboot"], "target": "layerscape/armv8_64b", "titles": [{"model": "LS1088A-RDB", "variant": "SD Card Boot", "vendor": "NXP"}], "version_code": "r20028-43d71ad93e", "version_number": "22.03.3"}