{"arch_packages": "mipsel_24kc", "build_at": "2023-12-04 06:01:55", "default_packages": ["base-files", "busybox", "ca-bundle", "dnsmasq", "dropbear", "firewall4", "fstools", "kmod-gpio-button-hotplug", "kmod-leds-gpio", "kmod-nft-offload", "kmod-rt2800-soc", "libc", "libgcc", "libustream-wolfssl", "logd", "mtd", "netifd", "nftables", "odhcp6c", "odhcpd-ipv6only", "opkg", "ppp", "ppp-mod-pppoe", "procd", "procd-seccomp", "procd-ujail", "swconfig", "uci", "uclient-fetch", "urandom-seed", "urngd", "wpad-basic-wolfssl"], "device_packages": ["jboot-tools", "kmod-usb2", "kmod-usb-ohci", "kmod-mt76x0e"], "id": "lava_lr-25g001", "image_path": "releases/22.03.6/targets/ramips/mt7620", "image_prefix": "openwrt-22.03.6-ramips-mt7620-lava_lr-25g001", "images": [{"filesystem": "initramfs", "name": "openwrt-22.03.6-ramips-mt7620-lava_lr-25g001-initramfs-kernel.bin", "sha256": "00483782c480dd8a4059407e4981ecd2982dacc6c415abfd3669de4085593636", "sha256_unsigned": "00483782c480dd8a4059407e4981ecd2982dacc6c415abfd3669de4085593636", "type": "kernel"}, {"filesystem": "squashfs", "name": "openwrt-22.03.6-ramips-mt7620-lava_lr-25g001-squashfs-factory.bin", "sha256": "62148a408080c7af310c5d14c5589ddd84384f94ee0781feaa2ba6e904b603f2", "sha256_unsigned": "62148a408080c7af310c5d14c5589ddd84384f94ee0781feaa2ba6e904b603f2", "type": "factory"}, {"filesystem": "squashfs", "name": "openwrt-22.03.6-ramips-mt7620-lava_lr-25g001-squashfs-sysupgrade.bin", "sha256": "713e2134fdc6e52ae7322090365f117469ef63bc6c52eeaee26537807832ee23", "sha256_unsigned": "b1dc6929f46239959a5fca4b1240146b1c7f6dc21ddaed67951471d0163a960f", "type": "sysupgrade"}], "metadata_version": 1, "source_date_epoch": 1700936337, "supported_devices": ["lava,lr-25g001"], "target": "ramips/mt7620", "titles": [{"model": "LR-25G001", "vendor": "LAVA"}], "version_code": "r20265-f85a79bcb4", "version_number": "22.03.6"}