{"arch_packages": "arm_cortex-a15_neon-vfpv4", "build_at": "2023-11-15 00:31:33", "default_packages": ["base-files", "busybox", "ca-bundle", "dnsmasq", "dropbear", "firewall4", "fstools", "kmod-ata-ahci", "kmod-ata-ahci-platform", "kmod-ath10k-ct", "kmod-gpio-button-hotplug", "kmod-leds-gpio", "kmod-nft-offload", "kmod-phy-qcom-ipq806x-usb", "kmod-usb-dwc3-qcom", "kmod-usb-ledtrig-usbport", "kmod-usb-ohci", "kmod-usb2", "kmod-usb3", "libc", "libgcc", "libustream-mbedtls", "logd", "mtd", "netifd", "nftables", "odhcp6c", "odhcpd-ipv6only", "opkg", "ppp", "ppp-mod-pppoe", "procd", "procd-seccomp", "procd-ujail", "swconfig", "uboot-envtools", "uci", "uclient-fetch", "urandom-seed", "urngd", "wpad-basic-mbedtls"], "device_packages": ["-kmod-ata-ahci", "-kmod-ata-ahci-platform", "-kmod-usb-ohci", "-kmod-usb2", "-kmod-usb-ledtrig-usbport", "-kmod-phy-qcom-ipq806x-usb", "-kmod-usb3", "-kmod-usb-dwc3-qcom", "ath10k-firmware-qca9984-ct"], "id": "nec_wg2600hp3", "image_path": "releases/23.05.2/targets/ipq806x/generic", "image_prefix": "openwrt-23.05.2-ipq806x-generic-nec_wg2600hp3", "images": [{"filesystem": "squashfs", "name": "openwrt-23.05.2-ipq806x-generic-nec_wg2600hp3-squashfs-sysupgrade.bin", "sha256": "ac8053d89a133b1e362f65ff9adbcdeb3b06c5e01ae368a213cfac2238cfbd59", "sha256_unsigned": "fca954e066f3f9f4bf15d034f4633edf2456399a3f8d668f834f3335172dd929", "type": "sysupgrade"}, {"filesystem": "initramfs", "name": "openwrt-23.05.2-ipq806x-generic-nec_wg2600hp3-initramfs-uImage", "sha256": "3988f21f18f45cb7a4e29071a2508a40ff2b674b4194952e4187cadfb80c6ac8", "sha256_unsigned": "3988f21f18f45cb7a4e29071a2508a40ff2b674b4194952e4187cadfb80c6ac8", "type": "kernel"}], "metadata_version": 1, "source_date_epoch": 1699969091, "supported_devices": ["nec,wg2600hp3"], "target": "ipq806x/generic", "titles": [{"model": "Aterm WG2600HP3", "vendor": "NEC Platforms"}], "version_code": "r23630-842932a63d", "version_number": "23.05.2"}