{"arch_packages": "arm_cortex-a9_vfpv3-d16", "build_at": "2023-04-13 06:47:54", "default_packages": ["base-files", "busybox", "ca-bundle", "dnsmasq", "dropbear", "firewall", "fstools", "ip6tables", "iptables", "kmod-gpio-button-hotplug", "kmod-ipt-offload", "libc", "libgcc", "libustream-wolfssl", "logd", "mtd", "netifd", "odhcp6c", "odhcpd-ipv6only", "opkg", "ppp", "ppp-mod-pppoe", "procd", "uboot-envtools", "uci", "uclient-fetch", "urandom-seed", "urngd"], "device_packages": [], "id": "globalscale_mirabox", "image_path": "releases/21.02.6/targets/mvebu/cortexa9", "image_prefix": "openwrt-21.02.6-mvebu-cortexa9-globalscale_mirabox", "images": [{"filesystem": "squashfs", "name": "openwrt-21.02.6-mvebu-cortexa9-globalscale_mirabox-squashfs-sysupgrade.bin", "sha256": "3f4a3182ed52e5269d4e3cac576235e6eec1b818afb125d9fee5abda3a76d368", "type": "sysupgrade"}, {"filesystem": "initramfs", "name": "openwrt-21.02.6-mvebu-cortexa9-globalscale_mirabox-initramfs-kernel.bin", "sha256": "29c2d0423467dc58222a69c2c6c405fc07aae1f19cd5ef34055b66e32d3fa591", "type": "kernel"}], "metadata_version": 1, "source_date_epoch": "1681043296", "supported_devices": ["globalscale,mirabox", "mirabox"], "target": "mvebu/cortexa9", "titles": [{"model": "Mirabox", "vendor": "Globalscale"}], "version_code": "r16842-bc99ce5b22", "version_number": "21.02.6"}