{"arch_packages": "arm_cortex-a7_neon-vfpv4", "build_at": "2023-04-10 18:30:06", "default_packages": ["ath10k-board-qca4019", "ath10k-firmware-qca4019-ct", "base-files", "busybox", "ca-bundle", "dnsmasq", "dropbear", "firewall4", "fstools", "kmod-ath10k-ct", "kmod-gpio-button-hotplug", "kmod-leds-gpio", "kmod-nft-offload", "kmod-usb-dwc3", "kmod-usb-dwc3-qcom", "kmod-usb3", "libc", "libgcc", "libustream-wolfssl", "logd", "mtd", "netifd", "nftables", "odhcp6c", "odhcpd-ipv6only", "opkg", "ppp", "ppp-mod-pppoe", "procd", "procd-seccomp", "procd-ujail", "swconfig", "uboot-envtools", "uci", "uclient-fetch", "urandom-seed", "urngd", "wpad-basic-wolfssl"], "device_packages": ["-kmod-ath10k-ct", "kmod-ath10k-ct-smallbuffers", "kmod-usb-ledtrig-usbport"], "id": "asus_rt-ac58u", "image_path": "releases/22.03.4/targets/ipq40xx/generic", "image_prefix": "openwrt-22.03.4-ipq40xx-generic-asus_rt-ac58u", "images": [{"filesystem": "squashfs", "name": "openwrt-22.03.4-ipq40xx-generic-asus_rt-ac58u-squashfs-sysupgrade.bin", "sha256": "ab7f46e42adf413c77ef8146be516a57d7a03294de370bdb488cc33c5dd0e748", "sha256_unsigned": "07ae24d57a54ca9a20fa9118004c24bdfc5660853bfeddcd5b5f226e476e37c3", "type": "sysupgrade"}, {"filesystem": "initramfs", "name": "openwrt-22.03.4-ipq40xx-generic-asus_rt-ac58u-initramfs-fit-uImage.itb", "sha256": "54d91db570ea61efd00c1332968a2e291308c5d935fcb6d9f6763a5e6465398e", "sha256_unsigned": "54d91db570ea61efd00c1332968a2e291308c5d935fcb6d9f6763a5e6465398e", "type": "kernel"}], "metadata_version": 1, "source_date_epoch": 1681043266, "supported_devices": ["asus,rt-ac58u"], "target": "ipq40xx/generic", "titles": [{"model": "RT-AC58U", "vendor": "ASUS"}, {"model": "RT-ACRH13", "vendor": "ASUS"}], "version_code": "r20123-38ccc47687", "version_number": "22.03.4"}