{"arch_packages": "mips64_octeonplus", "build_at": "2022-10-11 14:56:26", "default_packages": ["base-files", "busybox", "ca-bundle", "dnsmasq", "dropbear", "e2fsprogs", "firewall", "fstools", "ip6tables", "iptables", "kmod-ipt-offload", "libc", "libgcc", "libustream-wolfssl", "logd", "mkf2fs", "mtd", "netifd", "odhcp6c", "odhcpd-ipv6only", "opkg", "ppp", "ppp-mod-pppoe", "procd", "uci", "uclient-fetch", "urandom-seed", "urngd"], "device_packages": [], "id": "generic", "image_path": "releases/21.02.4/targets/octeon/generic", "image_prefix": "openwrt-21.02.4-octeon-generic", "images": [{"filesystem": "initramfs", "name": "openwrt-21.02.4-octeon-generic-initramfs-kernel.bin", "sha256": "4de2e5ea5c381f8c226f494fc003dc5330f2b01e8c959178de38dea35e419192", "type": "kernel"}], "metadata_version": 1, "source_date_epoch": "1665330221", "supported_devices": ["generic"], "target": "octeon/generic", "titles": [{"model": "Octeon", "vendor": "Generic"}], "version_code": "r16685-82ebc173b3", "version_number": "21.02.4"}