{"arch_packages": "mips_24kc", "build_at": "2023-01-04 23:41:31", "default_packages": ["base-files", "busybox", "ca-bundle", "dnsmasq", "dropbear", "firewall4", "fstools", "kmod-ath9k", "kmod-gpio-button-hotplug", "kmod-nft-offload", "libc", "libgcc", "libustream-wolfssl", "logd", "mtd", "netifd", "nftables", "odhcp6c", "odhcpd-ipv6only", "opkg", "ppp", "ppp-mod-pppoe", "procd", "procd-seccomp", "procd-ujail", "swconfig", "uboot-envtools", "uci", "uclient-fetch", "urandom-seed", "urngd", "wpad-basic-wolfssl"], "device_packages": ["kmod-usb2", "kmod-ath10k-ct", "ath10k-firmware-qca988x-ct"], "id": "dongwon_dw02-412h-128m", "image_path": "releases/22.03.3/targets/ath79/nand", "image_prefix": "openwrt-22.03.3-ath79-nand-dongwon_dw02-412h-128m", "images": [{"filesystem": "squashfs", "name": "openwrt-22.03.3-ath79-nand-dongwon_dw02-412h-128m-squashfs-factory.img", "sha256": "7cb10b175703434a21a0155496eb989e6b775c0459143ba7392b82c09326c6d1", "sha256_unsigned": "7cb10b175703434a21a0155496eb989e6b775c0459143ba7392b82c09326c6d1", "type": "factory"}, {"filesystem": "initramfs", "name": "openwrt-22.03.3-ath79-nand-dongwon_dw02-412h-128m-initramfs-kernel.bin", "sha256": "3310c5c93bcd761d9b10a43b7734cc734c80d214ad374b26adcb6cf4686dcb85", "sha256_unsigned": "3310c5c93bcd761d9b10a43b7734cc734c80d214ad374b26adcb6cf4686dcb85", "type": "kernel"}, {"filesystem": "squashfs", "name": "openwrt-22.03.3-ath79-nand-dongwon_dw02-412h-128m-squashfs-sysupgrade.bin", "sha256": "43bac5a30c970f65534a1337c5ef78a23cbb4f0694ba4be01d714e292bfc1580", "sha256_unsigned": "4ac5a14852cbac60e2306525b1efc832cc880f14d344874e51efa7b71b53788a", "type": "sysupgrade"}], "metadata_version": 1, "source_date_epoch": 1672705461, "supported_devices": ["dongwon,dw02-412h-128m"], "target": "ath79/nand", "titles": [{"model": "DW02-412H", "variant": "(128M)", "vendor": "Dongwon T&I"}, {"model": "GiGA WiFi home", "variant": "(128M)", "vendor": "KT"}], "version_code": "r20028-43d71ad93e", "version_number": "22.03.3"}