{"arch_packages": "mipsel_24kc", "build_at": "2022-10-17 15:39:23", "default_packages": ["base-files", "busybox", "ca-bundle", "dnsmasq", "dropbear", "firewall", "fstools", "ip6tables", "iptables", "kmod-gpio-button-hotplug", "kmod-ipt-offload", "kmod-leds-gpio", "kmod-rt2800-soc", "libc", "libgcc", "libustream-wolfssl", "logd", "mtd", "netifd", "odhcp6c", "odhcpd-ipv6only", "opkg", "ppp", "ppp-mod-pppoe", "procd", "swconfig", "uci", "uclient-fetch", "urandom-seed", "urngd", "wpad-basic-wolfssl"], "device_packages": [], "id": "omnima_miniembplug", "image_path": "releases/21.02.5/targets/ramips/rt305x", "image_prefix": "openwrt-21.02.5-ramips-rt305x-omnima_miniembplug", "images": [{"filesystem": "squashfs", "name": "openwrt-21.02.5-ramips-rt305x-omnima_miniembplug-squashfs-sysupgrade.bin", "sha256": "a1283774ee10374061739ae57310e2d8a7735225f287a6af53e048b520a9db79", "type": "sysupgrade"}, {"filesystem": "initramfs", "name": "openwrt-21.02.5-ramips-rt305x-omnima_miniembplug-initramfs-kernel.bin", "sha256": "3c6a30e3a41fa654f11f6ee40faff042e9c82274845f522207ec516285687f25", "type": "kernel"}], "metadata_version": 1, "source_date_epoch": "1665688598", "supported_devices": ["omnima,miniembplug", "miniembplug"], "target": "ramips/rt305x", "titles": [{"model": "MiniEMBPlug", "vendor": "Omnima"}], "version_code": "r16688-fa9a932fdb", "version_number": "21.02.5"}