{"arch_packages": "mipsel_24kc", "build_at": "2022-10-17 15:39:23", "default_packages": ["base-files", "busybox", "ca-bundle", "dnsmasq", "dropbear", "firewall", "fstools", "ip6tables", "iptables", "kmod-gpio-button-hotplug", "kmod-ipt-offload", "kmod-leds-gpio", "kmod-rt2800-soc", "libc", "libgcc", "libustream-wolfssl", "logd", "mtd", "netifd", "odhcp6c", "odhcpd-ipv6only", "opkg", "ppp", "ppp-mod-pppoe", "procd", "swconfig", "uci", "uclient-fetch", "urandom-seed", "urngd", "wpad-basic-wolfssl"], "device_packages": [], "id": "prolink_pwh2004", "image_path": "releases/21.02.5/targets/ramips/rt305x", "image_prefix": "openwrt-21.02.5-ramips-rt305x-prolink_pwh2004", "images": [{"filesystem": "squashfs", "name": "openwrt-21.02.5-ramips-rt305x-prolink_pwh2004-squashfs-sysupgrade.bin", "sha256": "1a1e7d61a591176a3ddc3551b7e43204a786fcc5ebb631ae3d73533b45f5f933", "type": "sysupgrade"}, {"filesystem": "initramfs", "name": "openwrt-21.02.5-ramips-rt305x-prolink_pwh2004-initramfs-kernel.bin", "sha256": "b3b4341309450a0f741d365b4815fe94e1415ecb60edbdfd6da4d6b4177c4e39", "type": "kernel"}], "metadata_version": 1, "source_date_epoch": "1665688598", "supported_devices": ["prolink,pwh2004", "pwh2004"], "target": "ramips/rt305x", "titles": [{"model": "PWH2004", "vendor": "Prolink"}], "version_code": "r16688-fa9a932fdb", "version_number": "21.02.5"}