{"arch_packages": "mipsel_24kc", "build_at": "2023-04-10 22:10:55", "default_packages": ["base-files", "busybox", "ca-bundle", "dnsmasq", "dropbear", "firewall4", "fstools", "kmod-gpio-button-hotplug", "kmod-leds-gpio", "kmod-nft-offload", "kmod-rt2800-soc", "libc", "libgcc", "libustream-wolfssl", "logd", "mtd", "netifd", "nftables", "odhcp6c", "odhcpd-ipv6only", "opkg", "ppp", "ppp-mod-pppoe", "procd", "procd-seccomp", "swconfig", "uci", "uclient-fetch", "urandom-seed", "urngd", "wpad-basic-wolfssl"], "device_packages": ["kmod-usb-ohci", "kmod-usb2"], "id": "hame_mpr-a2", "image_path": "releases/22.03.4/targets/ramips/rt305x", "image_prefix": "openwrt-22.03.4-ramips-rt305x-hame_mpr-a2", "images": [{"filesystem": "squashfs", "name": "openwrt-22.03.4-ramips-rt305x-hame_mpr-a2-squashfs-sysupgrade.bin", "sha256": "16a275c06fb7030b64e12557c9c21f78fa74efb30d1874faa31707a2756409ae", "sha256_unsigned": "ebc5cc127f71dc46b69a640e91d5f3fe9601fad143d741c5a29e24eaf289d446", "type": "sysupgrade"}, {"filesystem": "initramfs", "name": "openwrt-22.03.4-ramips-rt305x-hame_mpr-a2-initramfs-kernel.bin", "sha256": "c29f5650e128b0abf4699277268eb7814e5ed1373ec2d6a8b7eb571c6c2e34d2", "sha256_unsigned": "c29f5650e128b0abf4699277268eb7814e5ed1373ec2d6a8b7eb571c6c2e34d2", "type": "kernel"}], "metadata_version": 1, "source_date_epoch": 1681043266, "supported_devices": ["hame,mpr-a2", "mpr-a2"], "target": "ramips/rt305x", "titles": [{"model": "MPR", "variant": "A2", "vendor": "HAME"}], "version_code": "r20123-38ccc47687", "version_number": "22.03.4"}