{"arch_packages": "mipsel_24kc", "build_at": "2022-09-04 07:26:34", "default_packages": ["base-files", "busybox", "ca-bundle", "dnsmasq", "dropbear", "firewall4", "fstools", "kmod-gpio-button-hotplug", "kmod-leds-gpio", "kmod-mt7603", "kmod-nft-offload", "libc", "libgcc", "libustream-wolfssl", "logd", "mtd", "netifd", "nftables", "odhcp6c", "odhcpd-ipv6only", "opkg", "ppp", "ppp-mod-pppoe", "procd", "procd-seccomp", "procd-ujail", "swconfig", "uci", "uclient-fetch", "urandom-seed", "urngd", "wpad-basic-wolfssl"], "device_packages": ["kmod-usb2", "kmod-usb-ohci"], "id": "hak5_wifi-pineapple-mk7", "image_path": "releases/22.03.0/targets/ramips/mt76x8", "image_prefix": "openwrt-22.03.0-ramips-mt76x8-hak5_wifi-pineapple-mk7", "images": [{"filesystem": "initramfs", "name": "openwrt-22.03.0-ramips-mt76x8-hak5_wifi-pineapple-mk7-initramfs-kernel.bin", "sha256": "5fa7b1c68404902c3e9da275fd2c438c7a384458ee010086357671fb5fa2f748", "sha256_unsigned": "5fa7b1c68404902c3e9da275fd2c438c7a384458ee010086357671fb5fa2f748", "type": "kernel"}, {"filesystem": "squashfs", "name": "openwrt-22.03.0-ramips-mt76x8-hak5_wifi-pineapple-mk7-squashfs-sysupgrade.bin", "sha256": "30d64ec20caccc135b60bb94f92e290aa6975f8bd82437ffae966f569e459eb0", "sha256_unsigned": "e09f3b7e12e77b6b26dbb527c4d85173c15db0983cda9c0c43705c01c28c3acf", "type": "sysupgrade"}], "metadata_version": 1, "source_date_epoch": 1662173734, "supported_devices": ["hak5,wifi-pineapple-mk7", "wifi-pineapple-mk7"], "target": "ramips/mt76x8", "titles": [{"model": "WiFi Pineapple Mark 7", "vendor": "Hak5"}], "version_code": "r19685-512e76967f", "version_number": "22.03.0"}