{"arch_packages": "mipsel_24kc", "build_at": "2022-09-04 07:26:34", "default_packages": ["base-files", "busybox", "ca-bundle", "dnsmasq", "dropbear", "firewall4", "fstools", "kmod-gpio-button-hotplug", "kmod-leds-gpio", "kmod-mt7603", "kmod-nft-offload", "libc", "libgcc", "libustream-wolfssl", "logd", "mtd", "netifd", "nftables", "odhcp6c", "odhcpd-ipv6only", "opkg", "ppp", "ppp-mod-pppoe", "procd", "procd-seccomp", "procd-ujail", "swconfig", "uci", "uclient-fetch", "urandom-seed", "urngd", "wpad-basic-wolfssl"], "device_packages": [], "id": "hilink_hlk-7628n", "image_path": "releases/22.03.0/targets/ramips/mt76x8", "image_prefix": "openwrt-22.03.0-ramips-mt76x8-hilink_hlk-7628n", "images": [{"filesystem": "initramfs", "name": "openwrt-22.03.0-ramips-mt76x8-hilink_hlk-7628n-initramfs-kernel.bin", "sha256": "5a5de7ddbbca5fe41c55d9ff5a6649dae37b1cebd92f56c4263a73c5768e597a", "sha256_unsigned": "5a5de7ddbbca5fe41c55d9ff5a6649dae37b1cebd92f56c4263a73c5768e597a", "type": "kernel"}, {"filesystem": "squashfs", "name": "openwrt-22.03.0-ramips-mt76x8-hilink_hlk-7628n-squashfs-sysupgrade.bin", "sha256": "f1cef6c8c26a6fb2eccf304fe78def45707d3ac6a656b0d0599339606e788c34", "sha256_unsigned": "3abbe144b84c29b0fc45ab650782fffaa364b4dbab9abb7c57abed79fb0f9b81", "type": "sysupgrade"}], "metadata_version": 1, "source_date_epoch": 1662173734, "supported_devices": ["hilink,hlk-7628n"], "target": "ramips/mt76x8", "titles": [{"model": "HLK-7628N", "vendor": "HILINK"}], "version_code": "r19685-512e76967f", "version_number": "22.03.0"}