{"arch_packages": "mipsel_24kc", "build_at": "2021-10-26 01:37:07", "default_packages": ["base-files", "busybox", "ca-bundle", "dnsmasq", "dropbear", "firewall", "fstools", "ip6tables", "iptables", "kmod-gpio-button-hotplug", "kmod-ipt-offload", "kmod-leds-gpio", "kmod-mt7603", "libc", "libgcc", "libustream-wolfssl", "logd", "mtd", "netifd", "odhcp6c", "odhcpd-ipv6only", "opkg", "ppp", "ppp-mod-pppoe", "procd", "swconfig", "uci", "uclient-fetch", "urandom-seed", "urngd", "wpad-basic-wolfssl"], "device_packages": ["kmod-usb2", "kmod-usb-ohci", "kmod-usb-ledtrig-usbport"], "id": "hilink_hlk-7688a", "image_path": "releases/21.02.1/targets/ramips/mt76x8", "image_prefix": "openwrt-21.02.1-ramips-mt76x8-hilink_hlk-7688a", "images": [{"filesystem": "squashfs", "name": "openwrt-21.02.1-ramips-mt76x8-hilink_hlk-7688a-squashfs-sysupgrade.bin", "sha256": "f6ae2cccf5dbe004db24da0b4a6cb3b55477877e7dc8356ea74b1d01cf8a864d", "type": "sysupgrade"}, {"filesystem": "initramfs", "name": "openwrt-21.02.1-ramips-mt76x8-hilink_hlk-7688a-initramfs-kernel.bin", "sha256": "677fccc4d647e4fe4c7daf9265db143f5d06db60103d7f37355d70a7f67b80e5", "type": "kernel"}], "metadata_version": 1, "source_date_epoch": "1635066095", "supported_devices": ["hilink,hlk-7688a"], "target": "ramips/mt76x8", "titles": [{"model": "HLK-7688A", "vendor": "Hi-Link"}], "version_code": "r16325-88151b8303", "version_number": "21.02.1"}