{"arch_packages": "mips_24kc", "build_at": "2022-10-15 20:14:27", "default_packages": ["base-files", "busybox", "ca-bundle", "dnsmasq", "dropbear", "firewall4", "fstools", "kmod-ath9k", "kmod-gpio-button-hotplug", "kmod-nft-offload", "libc", "libgcc", "libustream-wolfssl", "logd", "mtd", "netifd", "nftables", "odhcp6c", "odhcpd-ipv6only", "opkg", "ppp", "ppp-mod-pppoe", "procd", "procd-seccomp", "procd-ujail", "swconfig", "uboot-envtools", "uci", "uclient-fetch", "urandom-seed", "urngd", "wpad-basic-wolfssl"], "device_packages": ["kmod-i2c-gpio", "kmod-gpio-pcf857x", "kmod-usb2", "kmod-usb-ledtrig-usbport", "rssileds"], "id": "alfa-network_n2q", "image_path": "releases/22.03.2/targets/ath79/generic", "image_prefix": "openwrt-22.03.2-ath79-generic-alfa-network_n2q", "images": [{"filesystem": "initramfs", "name": "openwrt-22.03.2-ath79-generic-alfa-network_n2q-initramfs-kernel.bin", "sha256": "7c5634bb9727ca5fb54b3e46fe37053cbe68ad98e0eff9a0c37370dd17a477d1", "sha256_unsigned": "7c5634bb9727ca5fb54b3e46fe37053cbe68ad98e0eff9a0c37370dd17a477d1", "type": "kernel"}, {"filesystem": "squashfs", "name": "openwrt-22.03.2-ath79-generic-alfa-network_n2q-squashfs-sysupgrade.bin", "sha256": "32b28a467a1753a28a1ec6b4c5a2f64b8a4e1a97598b54a3e851460b989d4238", "sha256_unsigned": "8cd6285a3d8c89cd886fde45e615a0a35966d147e3af0391409fa05be828e9e4", "type": "sysupgrade"}], "metadata_version": 1, "source_date_epoch": 1665787481, "supported_devices": ["alfa-network,n2q"], "target": "ath79/generic", "titles": [{"model": "N2Q", "vendor": "ALFA Network"}], "version_code": "r19803-9a599fee93", "version_number": "22.03.2"}