{"arch_packages": "mips_24kc", "build_at": "2022-10-15 20:14:27", "default_packages": ["base-files", "busybox", "ca-bundle", "dnsmasq", "dropbear", "firewall4", "fstools", "kmod-ath9k", "kmod-gpio-button-hotplug", "kmod-nft-offload", "libc", "libgcc", "libustream-wolfssl", "logd", "mtd", "netifd", "nftables", "odhcp6c", "odhcpd-ipv6only", "opkg", "ppp", "ppp-mod-pppoe", "procd", "procd-seccomp", "procd-ujail", "swconfig", "uboot-envtools", "uci", "uclient-fetch", "urandom-seed", "urngd", "wpad-basic-wolfssl"], "device_packages": ["kmod-ath10k-ct", "ath10k-firmware-qca9888-ct"], "id": "nec_wf1200cr", "image_path": "releases/22.03.2/targets/ath79/generic", "image_prefix": "openwrt-22.03.2-ath79-generic-nec_wf1200cr", "images": [{"filesystem": "initramfs", "name": "openwrt-22.03.2-ath79-generic-nec_wf1200cr-initramfs-kernel.bin", "sha256": "de583cee193114fa2646bfcb31e93ce2f74d4e366797bcf3a0c5f61b2156a98e", "sha256_unsigned": "de583cee193114fa2646bfcb31e93ce2f74d4e366797bcf3a0c5f61b2156a98e", "type": "kernel"}, {"filesystem": "squashfs", "name": "openwrt-22.03.2-ath79-generic-nec_wf1200cr-squashfs-sysupgrade.bin", "sha256": "ab26637aff83c177a9923993be62e7308b0d84b8065aa792661b775eae1fa9bf", "sha256_unsigned": "70d0dc97ebdfaed1e599679650d20e7a7d903ba1805c4d6eebaf97202f39f90b", "type": "sysupgrade"}, {"filesystem": "squashfs", "name": "openwrt-22.03.2-ath79-generic-nec_wf1200cr-squashfs-factory.bin", "sha256": "dee7b91281af4d562c440217ed8b7331542b07ccc41418c8ed6ef14e140a9043", "sha256_unsigned": "dee7b91281af4d562c440217ed8b7331542b07ccc41418c8ed6ef14e140a9043", "type": "factory"}], "metadata_version": 1, "source_date_epoch": 1665787481, "supported_devices": ["nec,wf1200cr"], "target": "ath79/generic", "titles": [{"model": "Aterm WF1200CR", "vendor": "NEC"}], "version_code": "r19803-9a599fee93", "version_number": "22.03.2"}