{"arch_packages": "arm_cortex-a9_vfpv3-d16", "build_at": "2022-10-09 23:14:56", "default_packages": ["base-files", "busybox", "ca-bundle", "dnsmasq", "dropbear", "e2fsprogs", "firewall4", "fstools", "kmod-nft-offload", "libc", "libgcc", "libustream-wolfssl", "logd", "mkf2fs", "mtd", "netifd", "nftables", "odhcp6c", "odhcpd-ipv6only", "opkg", "partx-utils", "ppp", "ppp-mod-pppoe", "procd", "procd-seccomp", "procd-ujail", "uci", "uclient-fetch", "urandom-seed", "urngd"], "device_packages": ["kmod-r8169", "kmod-rt2800-usb", "kmod-rtc-em3027", "kmod-usb-storage", "wpad-basic-wolfssl", "iwinfo"], "id": "compulab_trimslice", "image_path": "releases/22.03.1/targets/tegra/generic", "image_prefix": "openwrt-22.03.1-tegra-compulab_trimslice", "images": [{"filesystem": "ext4", "name": "openwrt-22.03.1-tegra-compulab_trimslice-ext4-sdcard.img.gz", "sha256": "7dc33c53e565eb19975995db511d99bc7d12fbbb0ff338cdb0b34b25e3fa8227", "sha256_unsigned": "ba72cbb20e6c35e167464b4d14b225c65cfdd82e6e3f8e34bd7e70a9c9ea96e7", "type": "sdcard"}, {"filesystem": "squashfs", "name": "openwrt-22.03.1-tegra-compulab_trimslice-squashfs-sdcard.img.gz", "sha256": "3f196b6bd60ea821c7916edb184c87f482ac5db3acf8ba4cb11afe6abe981f66", "sha256_unsigned": "834cdd7ec23aa360d768fe727fa8da74d3a3ba7ceb5c7efd5af518b82b311bba", "type": "sdcard"}], "metadata_version": 1, "source_date_epoch": 1665185696, "supported_devices": ["compulab,trimslice"], "target": "tegra/generic", "titles": [{"model": "TrimSlice", "vendor": "CompuLab"}], "version_code": "r19777-2853b6d652", "version_number": "22.03.1"}