{"arch_packages": "arm_xscale", "build_at": "2022-10-16 00:05:14", "default_packages": ["base-files", "busybox", "ca-bundle", "dnsmasq", "dropbear", "firewall4", "fstools", "kmod-nft-offload", "kmod-usb2", "libc", "libgcc", "libustream-wolfssl", "logd", "mtd", "netifd", "nftables", "odhcp6c", "odhcpd-ipv6only", "opkg", "ppp", "ppp-mod-pppoe", "procd", "procd-seccomp", "procd-ujail", "uboot-envtools", "uci", "uclient-fetch", "urandom-seed", "urngd"], "device_packages": ["kmod-ath9k", "kmod-gpio-button-hotplug", "kmod-mvsdio", "kmod-rtc-s35390a", "kmod-usb-ledtrig-usbport", "wpad-basic-wolfssl", "iwinfo"], "id": "checkpoint_l-50", "image_path": "releases/22.03.2/targets/kirkwood/generic", "image_prefix": "openwrt-22.03.2-kirkwood-checkpoint_l-50", "images": [{"filesystem": "squashfs", "name": "openwrt-22.03.2-kirkwood-checkpoint_l-50-squashfs-sysupgrade.bin", "sha256": "0abe5172fb36d5cba6acd3cf97f3eb148b3bdd84788c7edb84191a74690c00de", "sha256_unsigned": "716e803c02cb38c72dc898e31ceff43ac527fd30d5addf12e83da035d5cab968", "type": "sysupgrade"}, {"filesystem": "initramfs", "name": "openwrt-22.03.2-kirkwood-checkpoint_l-50-initramfs-uImage", "sha256": "0de896499a6e6154324247e805a5a4dda223d70fb65f20710d5a4053270e97e6", "sha256_unsigned": "0de896499a6e6154324247e805a5a4dda223d70fb65f20710d5a4053270e97e6", "type": "kernel"}], "metadata_version": 1, "source_date_epoch": 1665787481, "supported_devices": ["checkpoint,l-50"], "target": "kirkwood/generic", "titles": [{"model": "L-50", "vendor": "Check Point"}], "version_code": "r19803-9a599fee93", "version_number": "22.03.2"}